{"businesses": [{"id": "TiNdujj8V4qmBrUP1jqqFA", "alias": "dave-de-jour-encinitas", "name": "Dave de Jour", "image_url": "https://s3-media3.fl.yelpcdn.com/bphoto/dvzgpsl0oVPsus-vSUvOwA/o.jpg", "is_closed": false, "url": "https://www.yelp.com/biz/dave-de-jour-encinitas?adjust_creative=oncXGL2aPIKrtJdnWeFSnA&utm_campaign=yelp_api_v3&utm_medium=api_v3_business_search&utm_source=oncXGL2aPIKrtJdnWeFSnA", "review_count": 35, "categories": [{"alias": "foodstands", "title": "Food Stands"}, {"alias": "personalchefs", "title": "Personal Chefs"}], "rating": 4.5, "coordinates": {"latitude": 33.04568, "longitude": -117.29014}, "transactions": [], "price": "$", "location": {"address1": "", "address2": "", "address3": "", "city": "Encinitas", "zip_code": "92024", "country": "US", "state": "CA", "display_address": ["Encinitas, CA 92024"]}, "phone": "+18586990429", "display_phone": "(858) 699-0429", "distance": 2591.049815437307}, {"id": "vPcIwiC47UFibswDkWC4Og", "alias": "moonlight-beach-concession-stand-encinitas-2", "name": "Moonlight Beach Concession Stand", "image_url": "https://s3-media1.fl.yelpcdn.com/bphoto/1QYWV0R1HUm_EcFG8adMuA/o.jpg", "is_closed": false, "url": "https://www.yelp.com/biz/moonlight-beach-concession-stand-encinitas-2?adjust_creative=oncXGL2aPIKrtJdnWeFSnA&utm_campaign=yelp_api_v3&utm_medium=api_v3_business_search&utm_source=oncXGL2aPIKrtJdnWeFSnA", "review_count": 11, "categories": [{"alias": "foodstands", "title": "Food Stands"}], "rating": 4.5, "coordinates": {"latitude": 33.0485244, "longitude": -117.2971158}, "transactions": [], "price": "$", "location": {"address1": "400 B St", "address2": "", "address3": "", "city": "Encinitas", "zip_code": "92024", "country": "US", "state": "CA", "display_address": ["400 B St", "Encinitas, CA 92024"]}, "phone": "", "display_phone": "", "distance": 4254.012301720393}], "total": 2}