{"businesses": [{"id": "4CT1CpSrpp2njcLmIpIf0w", "alias": "draft-republic-carlsbad-carlsbad", "name": "Draft Republic Carlsbad", "image_url": "https://s3-media2.fl.yelpcdn.com/bphoto/Lt_9RHlsRD_uGOgtfufE_A/o.jpg", "is_closed": false, "url": "https://www.yelp.com/biz/draft-republic-carlsbad-carlsbad?adjust_creative=oncXGL2aPIKrtJdnWeFSnA&utm_campaign=yelp_api_v3&utm_medium=api_v3_business_search&utm_source=oncXGL2aPIKrtJdnWeFSnA", "review_count": 399, "categories": [{"alias": "comfortfood", "title": "Comfort Food"}, {"alias": "gastropubs", "title": "Gastropubs"}, {"alias": "newamerican", "title": "American (New)"}], "rating": 4.0, "coordinates": {"latitude": 33.12452, "longitude": -117.3244}, "transactions": [], "price": "$$", "location": {"address1": "5958 Avenida Encinas", "address2": null, "address3": null, "city": "Carlsbad", "zip_code": "92008", "country": "US", "state": "CA", "display_address": ["5958 Avenida Encinas", "Carlsbad, CA 92008"]}, "phone": "+17604484627", "display_phone": "(760) 448-4627", "distance": 3333.2347107908563}, {"id": "N1r-Ly84AtCfGknOeTAdUw", "alias": "the-compass-carlsbad", "name": "The Compass", "image_url": "https://s3-media4.fl.yelpcdn.com/bphoto/3ucdpGf5SPQ5tFrcjvSQOA/o.jpg", "is_closed": false, "url": "https://www.yelp.com/biz/the-compass-carlsbad?adjust_creative=oncXGL2aPIKrtJdnWeFSnA&utm_campaign=yelp_api_v3&utm_medium=api_v3_business_search&utm_source=oncXGL2aPIKrtJdnWeFSnA", "review_count": 970, "categories": [{"alias": "gastropubs", "title": "Gastropubs"}, {"alias": "tradamerican", "title": "American (Traditional)"}], "rating": 4.0, "coordinates": {"latitude": 33.1592717702151, "longitude": -117.350963309193}, "transactions": [], "price": "$$", "location": {"address1": "300 Carlsbad Village Dr", "address2": "Ste 202", "address3": "", "city": "Carlsbad", "zip_code": "92008", "country": "US", "state": "CA", "display_address": ["300 Carlsbad Village Dr", "Ste 202", "Carlsbad, CA 92008"]}, "phone": "+17604341900", "display_phone": "(760) 434-1900", "distance": 7129.903556849621}, {"id": "M64RxUJdSaFzQQEsJrR5Sg", "alias": "priority-public-house-encinitas", "name": "Priority Public House", "image_url": "https://s3-media3.fl.yelpcdn.com/bphoto/OGRXlg2QXW6wpqWbtcXa-A/o.jpg", "is_closed": false, "url": "https://www.yelp.com/biz/priority-public-house-encinitas?adjust_creative=oncXGL2aPIKrtJdnWeFSnA&utm_campaign=yelp_api_v3&utm_medium=api_v3_business_search&utm_source=oncXGL2aPIKrtJdnWeFSnA", "review_count": 435, "categories": [{"alias": "gastropubs", "title": "Gastropubs"}, {"alias": "newamerican", "title": "American (New)"}], "rating": 4.0, "coordinates": {"latitude": 33.05952, "longitude": -117.30043}, "transactions": [], "price": "$$", "location": {"address1": "576 N Coast Hwy 101", "address2": null, "address3": "", "city": "Encinitas", "zip_code": "92024", "country": "US", "state": "CA", "display_address": ["576 N Coast Hwy 101", "Encinitas, CA 92024"]}, "phone": "+17602301999", "display_phone": "(760) 230-1999", "distance": 7024.325452735303}, {"id": "UHds4K_S5vtM1vDTxcpYEQ", "alias": "urge-gastropub-and-whiskey-bank-oceanside", "name": "Urge Gastropub and Whiskey Bank", "image_url": "https://s3-media1.fl.yelpcdn.com/bphoto/3zxmQgq4YUUjVhyXi3iZdA/o.jpg", "is_closed": false, "url": "https://www.yelp.com/biz/urge-gastropub-and-whiskey-bank-oceanside?adjust_creative=oncXGL2aPIKrtJdnWeFSnA&utm_campaign=yelp_api_v3&utm_medium=api_v3_business_search&utm_source=oncXGL2aPIKrtJdnWeFSnA", "review_count": 629, "categories": [{"alias": "gastropubs", "title": "Gastropubs"}, {"alias": "cocktailbars", "title": "Cocktail Bars"}, {"alias": "whiskeybars", "title": "Whiskey Bars"}], "rating": 4.0, "coordinates": {"latitude": 33.1719442378322, "longitude": -117.359187524429}, "transactions": [], "price": "$$", "location": {"address1": "2002 S Coast Hwy", "address2": "", "address3": "", "city": "Oceanside", "zip_code": "92054", "country": "US", "state": "CA", "display_address": ["2002 S Coast Hwy", "Oceanside, CA 92054"]}, "phone": "+17604297424", "display_phone": "(760) 429-7424", "distance": 8600.546182929891}, {"id": "IknZriO2PTTfUcJB9LXnrw", "alias": "bread-and-barley-encinitas", "name": "Bread & Barley", "image_url": "https://s3-media3.fl.yelpcdn.com/bphoto/Vajt8bJEXbMPXM1HcEG8-w/o.jpg", "is_closed": false, "url": "https://www.yelp.com/biz/bread-and-barley-encinitas?adjust_creative=oncXGL2aPIKrtJdnWeFSnA&utm_campaign=yelp_api_v3&utm_medium=api_v3_business_search&utm_source=oncXGL2aPIKrtJdnWeFSnA", "review_count": 123, "categories": [{"alias": "cocktailbars", "title": "Cocktail Bars"}, {"alias": "gastropubs", "title": "Gastropubs"}], "rating": 4.0, "coordinates": {"latitude": 33.0590600478944, "longitude": -117.299880972852}, "transactions": [], "price": "$$", "location": {"address1": "542 N Coast Hwy 101", "address2": "", "address3": null, "city": "Encinitas", "zip_code": "92024", "country": "US", "state": "CA", "display_address": ["542 N Coast Hwy 101", "Encinitas, CA 92024"]}, "phone": "+17604875591", "display_phone": "(760) 487-5591", "distance": 7074.314325378196}, {"id": "pBLJIN4ks2eMdtLieikIwg", "alias": "flying-pig-pub-and-kitchen-vista-vista-2", "name": "Flying Pig Pub & Kitchen - Vista", "image_url": "https://s3-media3.fl.yelpcdn.com/bphoto/V6Ervm2X4Jkfh3WnO9C3kA/o.jpg", "is_closed": false, "url": "https://www.yelp.com/biz/flying-pig-pub-and-kitchen-vista-vista-2?adjust_creative=oncXGL2aPIKrtJdnWeFSnA&utm_campaign=yelp_api_v3&utm_medium=api_v3_business_search&utm_source=oncXGL2aPIKrtJdnWeFSnA", "review_count": 629, "categories": [{"alias": "gastropubs", "title": "Gastropubs"}, {"alias": "newamerican", "title": "American (New)"}], "rating": 4.0, "coordinates": {"latitude": 33.20038, "longitude": -117.24194}, "transactions": [], "price": "$$", "location": {"address1": "230 S Santa Fe", "address2": "", "address3": "", "city": "Vista", "zip_code": "92084", "country": "US", "state": "CA", "display_address": ["230 S Santa Fe", "Vista, CA 92084"]}, "phone": "+17606304311", "display_phone": "(760) 630-4311", "distance": 9733.216571049072}, {"id": "3GlVYOnWdZ4LZO7qgzO4gg", "alias": "partake-gastropub-vista", "name": "Partake Gastropub", "image_url": "https://s3-media3.fl.yelpcdn.com/bphoto/cWrr4g7RI2YPiDSt4mouWg/o.jpg", "is_closed": false, "url": "https://www.yelp.com/biz/partake-gastropub-vista?adjust_creative=oncXGL2aPIKrtJdnWeFSnA&utm_campaign=yelp_api_v3&utm_medium=api_v3_business_search&utm_source=oncXGL2aPIKrtJdnWeFSnA", "review_count": 640, "categories": [{"alias": "wine_bars", "title": "Wine Bars"}, {"alias": "newamerican", "title": "American (New)"}, {"alias": "gastropubs", "title": "Gastropubs"}], "rating": 4.5, "coordinates": {"latitude": 33.19483, "longitude": -117.236734}, "transactions": ["pickup", "delivery"], "price": "$$", "location": {"address1": "721 S Santa Fe Ave", "address2": "", "address3": "", "city": "Vista", "zip_code": "92083", "country": "US", "state": "CA", "display_address": ["721 S Santa Fe Ave", "Vista, CA 92083"]}, "phone": "+17604527217", "display_phone": "(760) 452-7217", "distance": 9430.288435631193}, {"id": "s1_WiwjWuuteaSmA5NpZmA", "alias": "bagby-beer-company-oceanside-14", "name": "Bagby Beer Company", "image_url": "https://s3-media2.fl.yelpcdn.com/bphoto/8bDmsoXf7bhSFzVqdSrJ-w/o.jpg", "is_closed": false, "url": "https://www.yelp.com/biz/bagby-beer-company-oceanside-14?adjust_creative=oncXGL2aPIKrtJdnWeFSnA&utm_campaign=yelp_api_v3&utm_medium=api_v3_business_search&utm_source=oncXGL2aPIKrtJdnWeFSnA", "review_count": 1037, "categories": [{"alias": "breweries", "title": "Breweries"}, {"alias": "gastropubs", "title": "Gastropubs"}, {"alias": "beerbar", "title": "Beer Bar"}], "rating": 4.0, "coordinates": {"latitude": 33.18923, "longitude": -117.37426}, "transactions": [], "price": "$$", "location": {"address1": "601 S Coast Hwy", "address2": "", "address3": "", "city": "Oceanside", "zip_code": "92054", "country": "US", "state": "CA", "display_address": ["601 S Coast Hwy", "Oceanside, CA 92054"]}, "phone": "+17605123372", "display_phone": "(760) 512-3372", "distance": 10943.682816660108}, {"id": "Pd8EpcYlKhysYkd9_7xDeg", "alias": "st-tropez-bistro-and-beyond-oceanside-2", "name": "St Tropez Bistro & Beyond", "image_url": "https://s3-media3.fl.yelpcdn.com/bphoto/hbnXxLWfjAPKcxqqQmS_nQ/o.jpg", "is_closed": false, "url": "https://www.yelp.com/biz/st-tropez-bistro-and-beyond-oceanside-2?adjust_creative=oncXGL2aPIKrtJdnWeFSnA&utm_campaign=yelp_api_v3&utm_medium=api_v3_business_search&utm_source=oncXGL2aPIKrtJdnWeFSnA", "review_count": 68, "categories": [{"alias": "modern_european", "title": "Modern European"}, {"alias": "breakfast_brunch", "title": "Breakfast & Brunch"}, {"alias": "gastropubs", "title": "Gastropubs"}], "rating": 4.0, "coordinates": {"latitude": 33.19025, "longitude": -117.3744}, "transactions": [], "price": "$$", "location": {"address1": "524 S Coast Hwy", "address2": null, "address3": "", "city": "Oceanside", "zip_code": "92054", "country": "US", "state": "CA", "display_address": ["524 S Coast Hwy", "Oceanside, CA 92054"]}, "phone": "+17609660985", "display_phone": "(760) 966-0985", "distance": 11015.796554879113}, {"id": "pStFm2NOx3XFNanoKlrIpA", "alias": "101-proof-oceanside-2", "name": "101 proof", "image_url": "https://s3-media4.fl.yelpcdn.com/bphoto/w1jT5sB1JMjNmPmUo1dxRA/o.jpg", "is_closed": false, "url": "https://www.yelp.com/biz/101-proof-oceanside-2?adjust_creative=oncXGL2aPIKrtJdnWeFSnA&utm_campaign=yelp_api_v3&utm_medium=api_v3_business_search&utm_source=oncXGL2aPIKrtJdnWeFSnA", "review_count": 33, "categories": [{"alias": "speakeasies", "title": "Speakeasies"}, {"alias": "cocktailbars", "title": "Cocktail Bars"}, {"alias": "gastropubs", "title": "Gastropubs"}], "rating": 3.5, "coordinates": {"latitude": 33.172158788577, "longitude": -117.359203333343}, "transactions": [], "price": "$$$", "location": {"address1": "2002 S Coast Hwy", "address2": "", "address3": null, "city": "Oceanside", "zip_code": "92054", "country": "US", "state": "CA", "display_address": ["2002 S Coast Hwy", "Oceanside, CA 92054"]}, "phone": "", "display_phone": "", "distance": 8617.09096163282}, {"id": "JZBSnJZKscRJ9hYlXjAWvg", "alias": "the-bier-garden-of-encinitas-encinitas", "name": "The Bier Garden of Encinitas", "image_url": "https://s3-media2.fl.yelpcdn.com/bphoto/shZZc_MuB8ElMDxypsB8Yg/o.jpg", "is_closed": false, "url": "https://www.yelp.com/biz/the-bier-garden-of-encinitas-encinitas?adjust_creative=oncXGL2aPIKrtJdnWeFSnA&utm_campaign=yelp_api_v3&utm_medium=api_v3_business_search&utm_source=oncXGL2aPIKrtJdnWeFSnA", "review_count": 642, "categories": [{"alias": "newamerican", "title": "American (New)"}, {"alias": "beer_and_wine", "title": "Beer, Wine & Spirits"}, {"alias": "gastropubs", "title": "Gastropubs"}], "rating": 4.0, "coordinates": {"latitude": 33.0439788958296, "longitude": -117.29331750824}, "transactions": ["pickup"], "price": "$$", "location": {"address1": "641 S Coast Hwy", "address2": "", "address3": "", "city": "Encinitas", "zip_code": "92024", "country": "US", "state": "CA", "display_address": ["641 S Coast Hwy", "Encinitas, CA 92024"]}, "phone": "+17606322437", "display_phone": "(760) 632-2437", "distance": 8684.501424029966}, {"id": "HbenatMYM8QAv1HkkslKVw", "alias": "urge-gastropub-and-common-house-san-marcos", "name": "Urge Gastropub & Common House", "image_url": "https://s3-media2.fl.yelpcdn.com/bphoto/FaAhNz1c5iYrX4CoP3H_qQ/o.jpg", "is_closed": false, "url": "https://www.yelp.com/biz/urge-gastropub-and-common-house-san-marcos?adjust_creative=oncXGL2aPIKrtJdnWeFSnA&utm_campaign=yelp_api_v3&utm_medium=api_v3_business_search&utm_source=oncXGL2aPIKrtJdnWeFSnA", "review_count": 465, "categories": [{"alias": "gastropubs", "title": "Gastropubs"}, {"alias": "bowling", "title": "Bowling"}, {"alias": "tradamerican", "title": "American (Traditional)"}], "rating": 3.5, "coordinates": {"latitude": 33.13549, "longitude": -117.15897}, "transactions": ["pickup", "delivery"], "price": "$$", "location": {"address1": "255 Redel Rd", "address2": null, "address3": "", "city": "San Marcos", "zip_code": "92078", "country": "US", "state": "CA", "display_address": ["255 Redel Rd", "San Marcos, CA 92078"]}, "phone": "+17607988822", "display_phone": "(760) 798-8822", "distance": 12213.290966340113}, {"id": "UFTbRgYpjDz2OLLJrmS9tA", "alias": "the-bellows-san-marcos-2", "name": "The Bellows", "image_url": "https://s3-media4.fl.yelpcdn.com/bphoto/Asnlr_WcT72mwgj_b19GyQ/o.jpg", "is_closed": false, "url": "https://www.yelp.com/biz/the-bellows-san-marcos-2?adjust_creative=oncXGL2aPIKrtJdnWeFSnA&utm_campaign=yelp_api_v3&utm_medium=api_v3_business_search&utm_source=oncXGL2aPIKrtJdnWeFSnA", "review_count": 438, "categories": [{"alias": "gastropubs", "title": "Gastropubs"}, {"alias": "tradamerican", "title": "American (Traditional)"}], "rating": 4.0, "coordinates": {"latitude": 33.122944, "longitude": -117.165618}, "transactions": [], "price": "$$", "location": {"address1": "803 S Twin Oaks Valley Rd", "address2": "Ste 107", "address3": "", "city": "San Marcos", "zip_code": "92078", "country": "US", "state": "CA", "display_address": ["803 S Twin Oaks Valley Rd", "Ste 107", "San Marcos, CA 92078"]}, "phone": "+17602903912", "display_phone": "(760) 290-3912", "distance": 11459.462912290048}, {"id": "ZEYlaeRbSTbCWiJJTtZXKg", "alias": "encinitas-ale-house-encinitas", "name": "Encinitas Ale House", "image_url": "https://s3-media3.fl.yelpcdn.com/bphoto/3HvWsP3uX5kCtP0dcTB6uw/o.jpg", "is_closed": false, "url": "https://www.yelp.com/biz/encinitas-ale-house-encinitas?adjust_creative=oncXGL2aPIKrtJdnWeFSnA&utm_campaign=yelp_api_v3&utm_medium=api_v3_business_search&utm_source=oncXGL2aPIKrtJdnWeFSnA", "review_count": 550, "categories": [{"alias": "pubs", "title": "Pubs"}, {"alias": "burgers", "title": "Burgers"}, {"alias": "gastropubs", "title": "Gastropubs"}], "rating": 4.0, "coordinates": {"latitude": 33.0385215, "longitude": -117.2929818}, "transactions": [], "price": "$$", "location": {"address1": "1044 S Coast Hwy 101", "address2": "", "address3": "", "city": "Encinitas", "zip_code": "92024", "country": "US", "state": "CA", "display_address": ["1044 S Coast Hwy 101", "Encinitas, CA 92024"]}, "phone": "+17609437180", "display_phone": "(760) 943-7180", "distance": 9289.2227739477}, {"id": "fNfI2dg2iiCBzDQDCXpTEw", "alias": "pacific-station-encinitas", "name": "Pacific Station", "image_url": "https://s3-media2.fl.yelpcdn.com/bphoto/wRqyiYNVxUvh4N1Fy89znA/o.jpg", "is_closed": false, "url": "https://www.yelp.com/biz/pacific-station-encinitas?adjust_creative=oncXGL2aPIKrtJdnWeFSnA&utm_campaign=yelp_api_v3&utm_medium=api_v3_business_search&utm_source=oncXGL2aPIKrtJdnWeFSnA", "review_count": 2, "categories": [{"alias": "gastropubs", "title": "Gastropubs"}], "rating": 3.5, "coordinates": {"latitude": 33.0435163782816, "longitude": -117.294290389728}, "transactions": [], "price": "$$", "location": {"address1": "687 S Coast Hwy", "address2": "Ste 223", "address3": "", "city": "Encinitas", "zip_code": "92024", "country": "US", "state": "CA", "display_address": ["687 S Coast Hwy", "Ste 223", "Encinitas, CA 92024"]}, "phone": "", "display_phone": "", "distance": 8740.83296522849}, {"id": "TO8TQJ7DH34ezyTlygco1g", "alias": "kellys-pub-san-diego-4", "name": "Kelly's Pub", "image_url": "https://s3-media2.fl.yelpcdn.com/bphoto/llts0mFnZqmH97jBbSc-QA/o.jpg", "is_closed": false, "url": "https://www.yelp.com/biz/kellys-pub-san-diego-4?adjust_creative=oncXGL2aPIKrtJdnWeFSnA&utm_campaign=yelp_api_v3&utm_medium=api_v3_business_search&utm_source=oncXGL2aPIKrtJdnWeFSnA", "review_count": 80, "categories": [{"alias": "burgers", "title": "Burgers"}, {"alias": "sportsbars", "title": "Sports Bars"}, {"alias": "gastropubs", "title": "Gastropubs"}], "rating": 3.0, "coordinates": {"latitude": 33.0050392, "longitude": -117.091217}, "transactions": ["delivery"], "price": "$$", "location": {"address1": "15817 Bernardo Ctr Dr", "address2": "Ste 113", "address3": "", "city": "San Diego", "zip_code": "92127", "country": "US", "state": "CA", "display_address": ["15817 Bernardo Ctr Dr", "Ste 113", "San Diego, CA 92127"]}, "phone": "+18586133649", "display_phone": "(858) 613-3649", "distance": 22556.72314716623}], "total": 16, "region": {"center": {"longitude": -117.28866577148438, "latitude": 33.12198326621279}}}