{"businesses": [{"id": "VJ2cq7ZPkdYXHWXhRaA3jg", "alias": "old-california-coffee-house-and-eatery-san-marcos", "name": "Old California Coffee House & Eatery", "image_url": "https://s3-media2.fl.yelpcdn.com/bphoto/DLNlQkug-MNOCC_u0gd_BQ/o.jpg", "is_closed": false, "url": "https://www.yelp.com/biz/old-california-coffee-house-and-eatery-san-marcos?adjust_creative=oncXGL2aPIKrtJdnWeFSnA&utm_campaign=yelp_api_v3&utm_medium=api_v3_business_search&utm_source=oncXGL2aPIKrtJdnWeFSnA", "review_count": 433, "categories": [{"alias": "coffee", "title": "Coffee & Tea"}, {"alias": "cafes", "title": "Cafes"}], "rating": 4.0, "coordinates": {"latitude": 33.1345929052726, "longitude": -117.191091949545}, "transactions": [], "price": "$", "location": {"address1": "1080 San Marcos Blvd", "address2": "Ste 176", "address3": "", "city": "San Marcos", "zip_code": "92078", "country": "US", "state": "CA", "display_address": ["1080 San Marcos Blvd", "Ste 176", "San Marcos, CA 92078"]}, "phone": "+17607442112", "display_phone": "(760) 744-2112", "distance": 1826.7633692019995}, {"id": "0EXN7oiwDkWFUO-ELvlRUw", "alias": "connies-vista", "name": "Connie's", "image_url": "https://s3-media2.fl.yelpcdn.com/bphoto/aAoh4qPVYIpVXFj5OoQq9w/o.jpg", "is_closed": false, "url": "https://www.yelp.com/biz/connies-vista?adjust_creative=oncXGL2aPIKrtJdnWeFSnA&utm_campaign=yelp_api_v3&utm_medium=api_v3_business_search&utm_source=oncXGL2aPIKrtJdnWeFSnA", "review_count": 320, "categories": [{"alias": "cafes", "title": "Cafes"}, {"alias": "tradamerican", "title": "American (Traditional)"}, {"alias": "breakfast_brunch", "title": "Breakfast & Brunch"}], "rating": 4.5, "coordinates": {"latitude": 33.1652801243252, "longitude": -117.245181798935}, "transactions": [], "price": "$", "location": {"address1": "1688 S Melrose Dr", "address2": "Ste 206", "address3": "", "city": "Vista", "zip_code": "92081", "country": "US", "state": "CA", "display_address": ["1688 S Melrose Dr", "Ste 206", "Vista, CA 92081"]}, "phone": "+17605971700", "display_phone": "(760) 597-1700", "distance": 7193.02976256009}, {"id": "lx80fowoZaS_8z9OkdAeLQ", "alias": "the-broken-yolk-cafe-san-marcos", "name": "The Broken Yolk Cafe", "image_url": "https://s3-media1.fl.yelpcdn.com/bphoto/nU-NiT_zfEj1OBmHSQ-NBA/o.jpg", "is_closed": false, "url": "https://www.yelp.com/biz/the-broken-yolk-cafe-san-marcos?adjust_creative=oncXGL2aPIKrtJdnWeFSnA&utm_campaign=yelp_api_v3&utm_medium=api_v3_business_search&utm_source=oncXGL2aPIKrtJdnWeFSnA", "review_count": 460, "categories": [{"alias": "breakfast_brunch", "title": "Breakfast & Brunch"}, {"alias": "cafes", "title": "Cafes"}, {"alias": "tradamerican", "title": "American (Traditional)"}], "rating": 3.5, "coordinates": {"latitude": 33.13951, "longitude": -117.19273}, "transactions": [], "price": "$$", "location": {"address1": "101 S. Las Posas Rd.", "address2": "", "address3": "", "city": "San Marcos", "zip_code": "92078", "country": "US", "state": "CA", "display_address": ["101 S. Las Posas Rd.", "San Marcos, CA 92078"]}, "phone": "+17604719655", "display_phone": "(760) 471-9655", "distance": 1832.5748307473698}, {"id": "RizbQf5fXWYND06KaIwElw", "alias": "chiosco-caff\u00e8-encinitas", "name": "Chiosco Caff\u00e8", "image_url": "https://s3-media4.fl.yelpcdn.com/bphoto/6wdTqbZi-nmI1hQo9YNzKg/o.jpg", "is_closed": false, "url": "https://www.yelp.com/biz/chiosco-caff%C3%A8-encinitas?adjust_creative=oncXGL2aPIKrtJdnWeFSnA&utm_campaign=yelp_api_v3&utm_medium=api_v3_business_search&utm_source=oncXGL2aPIKrtJdnWeFSnA", "review_count": 5, "categories": [{"alias": "cafes", "title": "Cafes"}], "rating": 5.0, "coordinates": {"latitude": 33.05391, "longitude": -117.261}, "transactions": [], "location": {"address1": "293 N El Camino Real", "address2": null, "address3": "", "city": "Encinitas", "zip_code": "92024", "country": "US", "state": "CA", "display_address": ["293 N El Camino Real", "Encinitas, CA 92024"]}, "phone": "", "display_phone": "", "distance": 12701.91582017583}, {"id": "TtCzoOxZn5NW1OxXDwd29Q", "alias": "san-marcos-deli-san-marcos", "name": "San Marcos Deli", "image_url": "https://s3-media1.fl.yelpcdn.com/bphoto/yArb8sSCWs1kvV6B6qc78w/o.jpg", "is_closed": false, "url": "https://www.yelp.com/biz/san-marcos-deli-san-marcos?adjust_creative=oncXGL2aPIKrtJdnWeFSnA&utm_campaign=yelp_api_v3&utm_medium=api_v3_business_search&utm_source=oncXGL2aPIKrtJdnWeFSnA", "review_count": 58, "categories": [{"alias": "delis", "title": "Delis"}, {"alias": "cafes", "title": "Cafes"}, {"alias": "sandwiches", "title": "Sandwiches"}], "rating": 4.5, "coordinates": {"latitude": 33.1406173706055, "longitude": -117.180389404297}, "transactions": ["delivery", "pickup"], "price": "$", "location": {"address1": "125 Vallecitos De Oro", "address2": "Ste K", "address3": "", "city": "San Marcos", "zip_code": "92069", "country": "US", "state": "CA", "display_address": ["125 Vallecitos De Oro", "Ste K", "San Marcos, CA 92069"]}, "phone": "+17607529844", "display_phone": "(760) 752-9844", "distance": 693.0183398996052}, {"id": "lCq5n2TStFAUBxYtLCXe9Q", "alias": "swamis-caf\u00e9-vista-vista", "name": "Swami's Caf\u00e9 Vista", "image_url": "https://s3-media2.fl.yelpcdn.com/bphoto/6IKyhIhVHRPPO-6nVkmZoA/o.jpg", "is_closed": false, "url": "https://www.yelp.com/biz/swamis-caf%C3%A9-vista-vista?adjust_creative=oncXGL2aPIKrtJdnWeFSnA&utm_campaign=yelp_api_v3&utm_medium=api_v3_business_search&utm_source=oncXGL2aPIKrtJdnWeFSnA", "review_count": 110, "categories": [{"alias": "breakfast_brunch", "title": "Breakfast & Brunch"}, {"alias": "cafes", "title": "Cafes"}], "rating": 3.5, "coordinates": {"latitude": 33.2004047, "longitude": -117.2449455}, "transactions": [], "price": "$$", "location": {"address1": "20 Main St", "address2": "#100", "address3": "", "city": "Vista", "zip_code": "92081", "country": "US", "state": "CA", "display_address": ["20 Main St", "#100", "Vista, CA 92081"]}, "phone": "+14422162985", "display_phone": "(442) 216-2985", "distance": 9356.870576953075}, {"id": "ZA7kIl0ClAGobsbGOVVoQg", "alias": "time-out-cafe-vista", "name": "Time Out Cafe", "image_url": "https://s3-media4.fl.yelpcdn.com/bphoto/n3hTsu2CMtOqjrW03DTZjQ/o.jpg", "is_closed": false, "url": "https://www.yelp.com/biz/time-out-cafe-vista?adjust_creative=oncXGL2aPIKrtJdnWeFSnA&utm_campaign=yelp_api_v3&utm_medium=api_v3_business_search&utm_source=oncXGL2aPIKrtJdnWeFSnA", "review_count": 193, "categories": [{"alias": "cafes", "title": "Cafes"}, {"alias": "breakfast_brunch", "title": "Breakfast & Brunch"}], "rating": 4.5, "coordinates": {"latitude": 33.192063, "longitude": -117.230805}, "transactions": [], "price": "$$", "location": {"address1": "1011 S Santa Fe Ave", "address2": "Ste A-B", "address3": "", "city": "Vista", "zip_code": "92083", "country": "US", "state": "CA", "display_address": ["1011 S Santa Fe Ave", "Ste A-B", "Vista, CA 92083"]}, "phone": "+17606304300", "display_phone": "(760) 630-4300", "distance": 7759.443523767036}, {"id": "CqqM_b4xiHwGsSWJcgQ8OQ", "alias": "french-corner-at-the-island-carlsbad", "name": "French Corner at The Island", "image_url": "https://s3-media1.fl.yelpcdn.com/bphoto/wehjPoCSC957RoXUniesdQ/o.jpg", "is_closed": false, "url": "https://www.yelp.com/biz/french-corner-at-the-island-carlsbad?adjust_creative=oncXGL2aPIKrtJdnWeFSnA&utm_campaign=yelp_api_v3&utm_medium=api_v3_business_search&utm_source=oncXGL2aPIKrtJdnWeFSnA", "review_count": 31, "categories": [{"alias": "french", "title": "French"}, {"alias": "creperies", "title": "Creperies"}, {"alias": "cafes", "title": "Cafes"}], "rating": 4.5, "coordinates": {"latitude": 33.1360951, "longitude": -117.2874636}, "transactions": [], "price": "$", "location": {"address1": "5808 Van Allen Way", "address2": "Ste 110", "address3": "", "city": "Carlsbad", "zip_code": "92008", "country": "US", "state": "CA", "display_address": ["5808 Van Allen Way", "Ste 110", "Carlsbad, CA 92008"]}, "phone": "+17605852037", "display_phone": "(760) 585-2037", "distance": 10584.231424056961}, {"id": "H9e_l61bXs-8ISEHNGUDhg", "alias": "swamis-caf\u00e9-escondido-escondido", "name": "Swami's Caf\u00e9 Escondido", "image_url": "https://s3-media2.fl.yelpcdn.com/bphoto/7T3jZ0JwgRxElRo_GN6JCw/o.jpg", "is_closed": false, "url": "https://www.yelp.com/biz/swamis-caf%C3%A9-escondido-escondido?adjust_creative=oncXGL2aPIKrtJdnWeFSnA&utm_campaign=yelp_api_v3&utm_medium=api_v3_business_search&utm_source=oncXGL2aPIKrtJdnWeFSnA", "review_count": 329, "categories": [{"alias": "breakfast_brunch", "title": "Breakfast & Brunch"}, {"alias": "cafes", "title": "Cafes"}], "rating": 3.0, "coordinates": {"latitude": 33.1213828, "longitude": -117.0826044}, "transactions": [], "price": "$$", "location": {"address1": "150 W Grand Ave", "address2": "", "address3": "", "city": "Escondido", "zip_code": "92025", "country": "US", "state": "CA", "display_address": ["150 W Grand Ave", "Escondido, CA 92025"]}, "phone": "+17607353333", "display_phone": "(760) 735-3333", "distance": 8738.291126727107}, {"id": "NQ4QOOTbYW9MfseqwRFZcQ", "alias": "2051-cafe-carlsbad", "name": "2051 Cafe", "image_url": "https://s3-media3.fl.yelpcdn.com/bphoto/2FSNyrghNITP3L21VkbrPw/o.jpg", "is_closed": false, "url": "https://www.yelp.com/biz/2051-cafe-carlsbad?adjust_creative=oncXGL2aPIKrtJdnWeFSnA&utm_campaign=yelp_api_v3&utm_medium=api_v3_business_search&utm_source=oncXGL2aPIKrtJdnWeFSnA", "review_count": 82, "categories": [{"alias": "cafes", "title": "Cafes"}, {"alias": "delis", "title": "Delis"}, {"alias": "italian", "title": "Italian"}], "rating": 5.0, "coordinates": {"latitude": 33.1224971661327, "longitude": -117.276416666667}, "transactions": [], "price": "$$", "location": {"address1": "2051 Palomar Airport Rd", "address2": "Ste 175", "address3": null, "city": "Carlsbad", "zip_code": "92011", "country": "US", "state": "CA", "display_address": ["2051 Palomar Airport Rd", "Ste 175", "Carlsbad, CA 92011"]}, "phone": "+17608142831", "display_phone": "(760) 814-2831", "distance": 9831.517865947755}, {"id": "d-tZcaHoQWe4bsxvLDHT3g", "alias": "yogurt-utopia-san-marcos", "name": "Yogurt Utopia", "image_url": "https://s3-media3.fl.yelpcdn.com/bphoto/wvy5hm0ji02dwdWb31_zzQ/o.jpg", "is_closed": false, "url": "https://www.yelp.com/biz/yogurt-utopia-san-marcos?adjust_creative=oncXGL2aPIKrtJdnWeFSnA&utm_campaign=yelp_api_v3&utm_medium=api_v3_business_search&utm_source=oncXGL2aPIKrtJdnWeFSnA", "review_count": 64, "categories": [{"alias": "icecream", "title": "Ice Cream & Frozen Yogurt"}, {"alias": "cafes", "title": "Cafes"}, {"alias": "acaibowls", "title": "Acai Bowls"}], "rating": 4.0, "coordinates": {"latitude": 33.09709, "longitude": -117.2002}, "transactions": [], "price": "$", "location": {"address1": "1523 San Elijo Rd S", "address2": "Ste 108", "address3": "", "city": "San Marcos", "zip_code": "92078", "country": "US", "state": "CA", "display_address": ["1523 San Elijo Rd S", "Ste 108", "San Marcos, CA 92078"]}, "phone": "+17605919479", "display_phone": "(760) 591-9479", "distance": 5536.698763890461}, {"id": "AYtf2IjgszPhwHmlnMAHgQ", "alias": "the-story-caffe-carlsbad", "name": "The Story Caffe", "image_url": "https://s3-media2.fl.yelpcdn.com/bphoto/MBT_9OXWuFHasK-eVmLXQQ/o.jpg", "is_closed": false, "url": "https://www.yelp.com/biz/the-story-caffe-carlsbad?adjust_creative=oncXGL2aPIKrtJdnWeFSnA&utm_campaign=yelp_api_v3&utm_medium=api_v3_business_search&utm_source=oncXGL2aPIKrtJdnWeFSnA", "review_count": 86, "categories": [{"alias": "cafes", "title": "Cafes"}], "rating": 4.5, "coordinates": {"latitude": 33.1110311787428, "longitude": -117.294607936909}, "transactions": [], "price": "$", "location": {"address1": "1350 Poinsettia Ln", "address2": null, "address3": "", "city": "Carlsbad", "zip_code": "92011", "country": "US", "state": "CA", "display_address": ["1350 Poinsettia Ln", "Carlsbad, CA 92011"]}, "phone": "+17609290029", "display_phone": "(760) 929-0029", "distance": 11793.802650557525}, {"id": "PePDtEhBC3QFfzoBsIgPoA", "alias": "coyote-cafe-vista", "name": "Coyote Cafe", "image_url": "https://s3-media2.fl.yelpcdn.com/bphoto/FNod93WlfXGH19LPkEdZBQ/o.jpg", "is_closed": false, "url": "https://www.yelp.com/biz/coyote-cafe-vista?adjust_creative=oncXGL2aPIKrtJdnWeFSnA&utm_campaign=yelp_api_v3&utm_medium=api_v3_business_search&utm_source=oncXGL2aPIKrtJdnWeFSnA", "review_count": 178, "categories": [{"alias": "comfortfood", "title": "Comfort Food"}, {"alias": "cafes", "title": "Cafes"}, {"alias": "tradamerican", "title": "American (Traditional)"}], "rating": 4.0, "coordinates": {"latitude": 33.2208236959789, "longitude": -117.245858771828}, "transactions": [], "price": "$$", "location": {"address1": "1450 N Santa Fe Ave", "address2": "", "address3": "", "city": "Vista", "zip_code": "92083", "country": "US", "state": "CA", "display_address": ["1450 N Santa Fe Ave", "Vista, CA 92083"]}, "phone": "+17607588724", "display_phone": "(760) 758-8724", "distance": 11104.921015516928}, {"id": "zfvGjWHxth969Rj_b_9yhg", "alias": "bombay-cafe-vista", "name": "Bombay Cafe", "image_url": "https://s3-media4.fl.yelpcdn.com/bphoto/SfID4NC-hodnkw7hPdFvMg/o.jpg", "is_closed": false, "url": "https://www.yelp.com/biz/bombay-cafe-vista?adjust_creative=oncXGL2aPIKrtJdnWeFSnA&utm_campaign=yelp_api_v3&utm_medium=api_v3_business_search&utm_source=oncXGL2aPIKrtJdnWeFSnA", "review_count": 252, "categories": [{"alias": "indpak", "title": "Indian"}, {"alias": "cafes", "title": "Cafes"}], "rating": 4.0, "coordinates": {"latitude": 33.21838, "longitude": -117.22677}, "transactions": [], "price": "$$", "location": {"address1": "1280 E Vista Way", "address2": "Ste 4", "address3": "", "city": "Vista", "zip_code": "92084", "country": "US", "state": "CA", "display_address": ["1280 E Vista Way", "Ste 4", "Vista, CA 92084"]}, "phone": "+17606306611", "display_phone": "(760) 630-6611", "distance": 9907.72665657541}, {"id": "gJzoi-QJ9d1LZGoaTpBRFQ", "alias": "board-and-brew-carlsbad-bressi-ranch-carlsbad", "name": "Board & Brew - Carlsbad Bressi Ranch", "image_url": "https://s3-media3.fl.yelpcdn.com/bphoto/mEivmuguEI3u-F7HMDuYBw/o.jpg", "is_closed": false, "url": "https://www.yelp.com/biz/board-and-brew-carlsbad-bressi-ranch-carlsbad?adjust_creative=oncXGL2aPIKrtJdnWeFSnA&utm_campaign=yelp_api_v3&utm_medium=api_v3_business_search&utm_source=oncXGL2aPIKrtJdnWeFSnA", "review_count": 508, "categories": [{"alias": "sandwiches", "title": "Sandwiches"}, {"alias": "beerbar", "title": "Beer Bar"}, {"alias": "cafes", "title": "Cafes"}], "rating": 4.0, "coordinates": {"latitude": 33.1274036, "longitude": -117.2526507}, "transactions": ["pickup"], "price": "$", "location": {"address1": "2681 Gateway Rd", "address2": "Ste 103", "address3": "", "city": "Carlsbad", "zip_code": "92009", "country": "US", "state": "CA", "display_address": ["2681 Gateway Rd", "Ste 103", "Carlsbad, CA 92009"]}, "phone": "+17609292739", "display_phone": "(760) 929-2739", "distance": 7552.971701540556}, {"id": "ses6FCx_GEhvAozSmllFeA", "alias": "goodonya-organic-eatery-encinitas-2", "name": "GOODONYA\u00ae Organic Eatery", "image_url": "https://s3-media2.fl.yelpcdn.com/bphoto/x9zZ3tBGVU66cDhF5rN4kw/o.jpg", "is_closed": false, "url": "https://www.yelp.com/biz/goodonya-organic-eatery-encinitas-2?adjust_creative=oncXGL2aPIKrtJdnWeFSnA&utm_campaign=yelp_api_v3&utm_medium=api_v3_business_search&utm_source=oncXGL2aPIKrtJdnWeFSnA", "review_count": 366, "categories": [{"alias": "sandwiches", "title": "Sandwiches"}, {"alias": "cafes", "title": "Cafes"}, {"alias": "bars", "title": "Bars"}], "rating": 4.5, "coordinates": {"latitude": 33.0386973, "longitude": -117.2927026}, "transactions": ["pickup", "restaurant_reservation"], "price": "$$", "location": {"address1": "1051 S Coast Hwy 101", "address2": "", "address3": "", "city": "Encinitas", "zip_code": "92024", "country": "US", "state": "CA", "display_address": ["1051 S Coast Hwy 101", "Encinitas, CA 92024"]}, "phone": "+18582648550", "display_phone": "(858) 264-8550", "distance": 15951.418071486449}, {"id": "wA9zRrn7qLanrZ2dA_DFLg", "alias": "lush-lounge-vista", "name": "Lush Lounge", "image_url": "https://s3-media1.fl.yelpcdn.com/bphoto/Z29HnV4FCbZrJFZHNIQ84A/o.jpg", "is_closed": false, "url": "https://www.yelp.com/biz/lush-lounge-vista?adjust_creative=oncXGL2aPIKrtJdnWeFSnA&utm_campaign=yelp_api_v3&utm_medium=api_v3_business_search&utm_source=oncXGL2aPIKrtJdnWeFSnA", "review_count": 244, "categories": [{"alias": "cafes", "title": "Cafes"}, {"alias": "coffee", "title": "Coffee & Tea"}, {"alias": "breakfast_brunch", "title": "Breakfast & Brunch"}], "rating": 4.0, "coordinates": {"latitude": 33.203145, "longitude": -117.241053}, "transactions": ["delivery", "pickup"], "price": "$", "location": {"address1": "324 Main St", "address2": "", "address3": "", "city": "Vista", "zip_code": "92084", "country": "US", "state": "CA", "display_address": ["324 Main St", "Vista, CA 92084"]}, "phone": "+17602127675", "display_phone": "(760) 212-7675", "distance": 9310.696971782641}, {"id": "ULJp8Bc_7iLHNz6Xzi2eRw", "alias": "thyme-in-the-ranch-rancho-santa-fe", "name": "Thyme In The Ranch", "image_url": "https://s3-media2.fl.yelpcdn.com/bphoto/_sTUi7VZBtR4aH7h53U5zw/o.jpg", "is_closed": false, "url": "https://www.yelp.com/biz/thyme-in-the-ranch-rancho-santa-fe?adjust_creative=oncXGL2aPIKrtJdnWeFSnA&utm_campaign=yelp_api_v3&utm_medium=api_v3_business_search&utm_source=oncXGL2aPIKrtJdnWeFSnA", "review_count": 205, "categories": [{"alias": "breakfast_brunch", "title": "Breakfast & Brunch"}, {"alias": "bakeries", "title": "Bakeries"}, {"alias": "cafes", "title": "Cafes"}], "rating": 4.5, "coordinates": {"latitude": 33.019147, "longitude": -117.20322}, "transactions": [], "price": "$$", "location": {"address1": "16905 Avenida De Acacias", "address2": "", "address3": "", "city": "Rancho Santa Fe", "zip_code": "92067", "country": "US", "state": "CA", "display_address": ["16905 Avenida De Acacias", "Rancho Santa Fe, CA 92067"]}, "phone": "+18587590747", "display_phone": "(858) 759-0747", "distance": 13889.267778833933}, {"id": "LxiFye2ZVQzQVqCALcrRag", "alias": "healthy-creations-cafe-encinitas-3", "name": "Healthy Creations Cafe", "image_url": "https://s3-media3.fl.yelpcdn.com/bphoto/_4fYeVIPRUCsgg6GQKJPuA/o.jpg", "is_closed": false, "url": "https://www.yelp.com/biz/healthy-creations-cafe-encinitas-3?adjust_creative=oncXGL2aPIKrtJdnWeFSnA&utm_campaign=yelp_api_v3&utm_medium=api_v3_business_search&utm_source=oncXGL2aPIKrtJdnWeFSnA", "review_count": 369, "categories": [{"alias": "gluten_free", "title": "Gluten-Free"}, {"alias": "juicebars", "title": "Juice Bars & Smoothies"}, {"alias": "cafes", "title": "Cafes"}], "rating": 4.5, "coordinates": {"latitude": 33.055608, "longitude": -117.2624121}, "transactions": [], "price": "$$", "location": {"address1": "376 N El Camino Real", "address2": "", "address3": "", "city": "Encinitas", "zip_code": "92024", "country": "US", "state": "CA", "display_address": ["376 N El Camino Real", "Encinitas, CA 92024"]}, "phone": "+17604790500", "display_phone": "(760) 479-0500", "distance": 12703.483357333133}, {"id": "LX5IesxWlR8BMGVuGw84iA", "alias": "swamis-caf\u00e9-carlsbad-carlsbad", "name": "Swami's Caf\u00e9 Carlsbad", "image_url": "https://s3-media4.fl.yelpcdn.com/bphoto/fiV3V6ueIzlf8dedh1Z7ZA/o.jpg", "is_closed": false, "url": "https://www.yelp.com/biz/swamis-caf%C3%A9-carlsbad-carlsbad?adjust_creative=oncXGL2aPIKrtJdnWeFSnA&utm_campaign=yelp_api_v3&utm_medium=api_v3_business_search&utm_source=oncXGL2aPIKrtJdnWeFSnA", "review_count": 452, "categories": [{"alias": "breakfast_brunch", "title": "Breakfast & Brunch"}, {"alias": "cafes", "title": "Cafes"}], "rating": 3.5, "coordinates": {"latitude": 33.1604011, "longitude": -117.3524211}, "transactions": [], "price": "$$", "location": {"address1": "2780 Carlsbad Blvd", "address2": "", "address3": "", "city": "Carlsbad", "zip_code": "92008", "country": "US", "state": "CA", "display_address": ["2780 Carlsbad Blvd", "Carlsbad, CA 92008"]}, "phone": "+17604347455", "display_phone": "(760) 434-7455", "distance": 16806.036661819093}, {"id": "JZ4bqdJALxX3Gj3vrRdcjQ", "alias": "naked-cafe-carlsbad", "name": "Naked Cafe", "image_url": "https://s3-media1.fl.yelpcdn.com/bphoto/Q_ZskFqIjztV09OqABGeKA/o.jpg", "is_closed": false, "url": "https://www.yelp.com/biz/naked-cafe-carlsbad?adjust_creative=oncXGL2aPIKrtJdnWeFSnA&utm_campaign=yelp_api_v3&utm_medium=api_v3_business_search&utm_source=oncXGL2aPIKrtJdnWeFSnA", "review_count": 571, "categories": [{"alias": "gluten_free", "title": "Gluten-Free"}, {"alias": "cafes", "title": "Cafes"}], "rating": 4.0, "coordinates": {"latitude": 33.159171, "longitude": -117.350148}, "transactions": [], "price": "$$", "location": {"address1": "300 Carlsbad Village Dr", "address2": "Ste 107A", "address3": "", "city": "Carlsbad", "zip_code": "92008", "country": "US", "state": "CA", "display_address": ["300 Carlsbad Village Dr", "Ste 107A", "Carlsbad, CA 92008"]}, "phone": "+17607207866", "display_phone": "(760) 720-7866", "distance": 16579.475667686624}, {"id": "dVC5nOsqbKgIU1MgRUNxVg", "alias": "swamis-cafe-encinitas-blvd-encinitas", "name": "Swami's Cafe Encinitas Blvd", "image_url": "https://s3-media1.fl.yelpcdn.com/bphoto/ja3IV42qCTnTGXwCe1M1rQ/o.jpg", "is_closed": false, "url": "https://www.yelp.com/biz/swamis-cafe-encinitas-blvd-encinitas?adjust_creative=oncXGL2aPIKrtJdnWeFSnA&utm_campaign=yelp_api_v3&utm_medium=api_v3_business_search&utm_source=oncXGL2aPIKrtJdnWeFSnA", "review_count": 190, "categories": [{"alias": "cafes", "title": "Cafes"}, {"alias": "breakfast_brunch", "title": "Breakfast & Brunch"}], "rating": 3.5, "coordinates": {"latitude": 33.0466239751093, "longitude": -117.256423318596}, "transactions": [], "price": "$$", "location": {"address1": "1506 Encinitas Blvd", "address2": "", "address3": "", "city": "Encinitas", "zip_code": "92024", "country": "US", "state": "CA", "display_address": ["1506 Encinitas Blvd", "Encinitas, CA 92024"]}, "phone": "+17609422741", "display_phone": "(760) 942-2741", "distance": 13089.036284449498}, {"id": "bMaLUzqesduPD1ARGOgPxQ", "alias": "donut-touch-san-diego-5", "name": "Donut Touch", "image_url": "https://s3-media2.fl.yelpcdn.com/bphoto/m7nTYvu3UmLlUPXbhEfuCg/o.jpg", "is_closed": false, "url": "https://www.yelp.com/biz/donut-touch-san-diego-5?adjust_creative=oncXGL2aPIKrtJdnWeFSnA&utm_campaign=yelp_api_v3&utm_medium=api_v3_business_search&utm_source=oncXGL2aPIKrtJdnWeFSnA", "review_count": 155, "categories": [{"alias": "cafes", "title": "Cafes"}, {"alias": "bagels", "title": "Bagels"}, {"alias": "donuts", "title": "Donuts"}], "rating": 4.5, "coordinates": {"latitude": 33.0158046023322, "longitude": -117.110487349871}, "transactions": [], "price": "$", "location": {"address1": "16621 Dove Canyon Rd", "address2": "Ste 116", "address3": "", "city": "San Diego", "zip_code": "92127", "country": "US", "state": "CA", "display_address": ["16621 Dove Canyon Rd", "Ste 116", "San Diego, CA 92127"]}, "phone": "+18583857900", "display_phone": "(858) 385-7900", "distance": 15156.27037884616}, {"id": "Uo8gJlSMSqIe_wiGxsim9w", "alias": "wholly-crepe-poway", "name": "Wholly Crepe", "image_url": "https://s3-media1.fl.yelpcdn.com/bphoto/ANYgfI0x6QNu0fPe2Wxm6A/o.jpg", "is_closed": false, "url": "https://www.yelp.com/biz/wholly-crepe-poway?adjust_creative=oncXGL2aPIKrtJdnWeFSnA&utm_campaign=yelp_api_v3&utm_medium=api_v3_business_search&utm_source=oncXGL2aPIKrtJdnWeFSnA", "review_count": 225, "categories": [{"alias": "creperies", "title": "Creperies"}, {"alias": "breakfast_brunch", "title": "Breakfast & Brunch"}, {"alias": "cafes", "title": "Cafes"}], "rating": 4.5, "coordinates": {"latitude": 32.9689811, "longitude": -117.0361198}, "transactions": [], "price": "$", "location": {"address1": "14045 Midland Rd", "address2": null, "address3": "", "city": "Poway", "zip_code": "92064", "country": "US", "state": "CA", "display_address": ["14045 Midland Rd", "Poway, CA 92064"]}, "phone": "+19517603041", "display_phone": "(951) 760-3041", "distance": 23056.716961889197}, {"id": "fh7AxOjyqxezA4GzjRhKgg", "alias": "naked-cafe-encinitas", "name": "Naked Cafe", "image_url": "https://s3-media1.fl.yelpcdn.com/bphoto/tCSG94vT_TVhFGIRlbpseg/o.jpg", "is_closed": false, "url": "https://www.yelp.com/biz/naked-cafe-encinitas?adjust_creative=oncXGL2aPIKrtJdnWeFSnA&utm_campaign=yelp_api_v3&utm_medium=api_v3_business_search&utm_source=oncXGL2aPIKrtJdnWeFSnA", "review_count": 228, "categories": [{"alias": "vegetarian", "title": "Vegetarian"}, {"alias": "gluten_free", "title": "Gluten-Free"}, {"alias": "cafes", "title": "Cafes"}], "rating": 4.0, "coordinates": {"latitude": 33.053811, "longitude": -117.262665}, "transactions": [], "price": "$$", "location": {"address1": "288-C N El Camino Real", "address2": "", "address3": "", "city": "Encinitas", "zip_code": "92024", "country": "US", "state": "CA", "display_address": ["288-C N El Camino Real", "Encinitas, CA 92024"]}, "phone": "+17606357866", "display_phone": "(760) 635-7866", "distance": 12823.027927241757}, {"id": "e6uBoyy6gl_dX5tq60PGDg", "alias": "the-encinitas-cafe-encinitas", "name": "The Encinitas Cafe", "image_url": "https://s3-media1.fl.yelpcdn.com/bphoto/hcRbnCNcRg0LVvdi2fgDeQ/o.jpg", "is_closed": false, "url": "https://www.yelp.com/biz/the-encinitas-cafe-encinitas?adjust_creative=oncXGL2aPIKrtJdnWeFSnA&utm_campaign=yelp_api_v3&utm_medium=api_v3_business_search&utm_source=oncXGL2aPIKrtJdnWeFSnA", "review_count": 378, "categories": [{"alias": "tradamerican", "title": "American (Traditional)"}, {"alias": "cafes", "title": "Cafes"}, {"alias": "burgers", "title": "Burgers"}], "rating": 4.0, "coordinates": {"latitude": 33.0454942, "longitude": -117.2936288}, "transactions": [], "price": "$", "location": {"address1": "531 S Coast Hwy 101", "address2": "", "address3": "", "city": "Encinitas", "zip_code": "92024", "country": "US", "state": "CA", "display_address": ["531 S Coast Hwy 101", "Encinitas, CA 92024"]}, "phone": "+17606320919", "display_phone": "(760) 632-0919", "distance": 15475.2161747983}, {"id": "GSDK2mEWNNfyKbg_cu19xA", "alias": "hide-away-cafe-solana-beach-2", "name": "Hide Away Cafe", "image_url": "https://s3-media4.fl.yelpcdn.com/bphoto/EeYKNpkSjCMqw2XpYnDXRg/o.jpg", "is_closed": false, "url": "https://www.yelp.com/biz/hide-away-cafe-solana-beach-2?adjust_creative=oncXGL2aPIKrtJdnWeFSnA&utm_campaign=yelp_api_v3&utm_medium=api_v3_business_search&utm_source=oncXGL2aPIKrtJdnWeFSnA", "review_count": 386, "categories": [{"alias": "breakfast_brunch", "title": "Breakfast & Brunch"}, {"alias": "bakeries", "title": "Bakeries"}, {"alias": "cafes", "title": "Cafes"}], "rating": 4.5, "coordinates": {"latitude": 32.9912206983526, "longitude": -117.272230595875}, "transactions": [], "price": "$", "location": {"address1": "150 S Acacia Ave", "address2": null, "address3": "", "city": "Solana Beach", "zip_code": "92075", "country": "US", "state": "CA", "display_address": ["150 S Acacia Ave", "Solana Beach, CA 92075"]}, "phone": "+18587553388", "display_phone": "(858) 755-3388", "distance": 19140.39091935527}, {"id": "oEkwECV7boOXALRsg4yeFA", "alias": "marketplace-cafe-escondido-4", "name": "Marketplace Cafe", "image_url": "https://s3-media1.fl.yelpcdn.com/bphoto/LnMQRIdcbtM23Z_GFhr1gg/o.jpg", "is_closed": false, "url": "https://www.yelp.com/biz/marketplace-cafe-escondido-4?adjust_creative=oncXGL2aPIKrtJdnWeFSnA&utm_campaign=yelp_api_v3&utm_medium=api_v3_business_search&utm_source=oncXGL2aPIKrtJdnWeFSnA", "review_count": 129, "categories": [{"alias": "newamerican", "title": "American (New)"}, {"alias": "cafes", "title": "Cafes"}], "rating": 4.0, "coordinates": {"latitude": 33.071171462387, "longitude": -117.065258397662}, "transactions": [], "price": "$$", "location": {"address1": "270 E Via Rancho Pkwy", "address2": "", "address3": "Nordstrom", "city": "Escondido", "zip_code": "92025", "country": "US", "state": "CA", "display_address": ["270 E Via Rancho Pkwy", "Nordstrom", "Escondido, CA 92025"]}, "phone": "+17607400170", "display_phone": "(760) 740-0170", "distance": 12747.614107641792}, {"id": "9AJfO9Y3ObUZjqDS6LNW1g", "alias": "board-and-brew-carlsbad-village-carlsbad", "name": "Board & Brew - Carlsbad Village", "image_url": "https://s3-media1.fl.yelpcdn.com/bphoto/81gjco-FbCgGmrrvjTfyCg/o.jpg", "is_closed": false, "url": "https://www.yelp.com/biz/board-and-brew-carlsbad-village-carlsbad?adjust_creative=oncXGL2aPIKrtJdnWeFSnA&utm_campaign=yelp_api_v3&utm_medium=api_v3_business_search&utm_source=oncXGL2aPIKrtJdnWeFSnA", "review_count": 709, "categories": [{"alias": "sandwiches", "title": "Sandwiches"}, {"alias": "beerbar", "title": "Beer Bar"}, {"alias": "cafes", "title": "Cafes"}], "rating": 4.5, "coordinates": {"latitude": 33.1566912, "longitude": -117.3502563}, "transactions": [], "price": "$", "location": {"address1": "201 Oak Ave", "address2": null, "address3": "", "city": "Carlsbad", "zip_code": "92008", "country": "US", "state": "CA", "display_address": ["201 Oak Ave", "Carlsbad, CA 92008"]}, "phone": "+17604344466", "display_phone": "(760) 434-4466", "distance": 16559.38492315724}, {"id": "Edv644a30618d89v_ZkCJw", "alias": "copa-vida-carlsbad", "name": "Copa Vida", "image_url": "https://s3-media2.fl.yelpcdn.com/bphoto/73C1KIHxjlR3HYO-gffooA/o.jpg", "is_closed": false, "url": "https://www.yelp.com/biz/copa-vida-carlsbad?adjust_creative=oncXGL2aPIKrtJdnWeFSnA&utm_campaign=yelp_api_v3&utm_medium=api_v3_business_search&utm_source=oncXGL2aPIKrtJdnWeFSnA", "review_count": 14, "categories": [{"alias": "coffee", "title": "Coffee & Tea"}, {"alias": "cafes", "title": "Cafes"}], "rating": 4.5, "coordinates": {"latitude": 33.1268348693848, "longitude": -117.326843261719}, "transactions": [], "price": "$$", "location": {"address1": "5600 Avenida Encinas", "address2": null, "address3": "", "city": "Carlsbad", "zip_code": "92008", "country": "US", "state": "CA", "display_address": ["5600 Avenida Encinas", "Carlsbad, CA 92008"]}, "phone": "+17608142330", "display_phone": "(760) 814-2330", "distance": 14367.017080038786}, {"id": "eWD1N_M4Y6y-CtxRP4q-hA", "alias": "come-on-over-cafe-oceanside-7", "name": "Come On Over Cafe", "image_url": "https://s3-media4.fl.yelpcdn.com/bphoto/_ZSNASZ82pH94qGFUlzccA/o.jpg", "is_closed": false, "url": "https://www.yelp.com/biz/come-on-over-cafe-oceanside-7?adjust_creative=oncXGL2aPIKrtJdnWeFSnA&utm_campaign=yelp_api_v3&utm_medium=api_v3_business_search&utm_source=oncXGL2aPIKrtJdnWeFSnA", "review_count": 62, "categories": [{"alias": "cafes", "title": "Cafes"}, {"alias": "sandwiches", "title": "Sandwiches"}, {"alias": "coffee", "title": "Coffee & Tea"}], "rating": 5.0, "coordinates": {"latitude": 33.199474, "longitude": -117.3457638}, "transactions": [], "price": "$", "location": {"address1": "2420 Industry St", "address2": null, "address3": "", "city": "Oceanside", "zip_code": "92054", "country": "US", "state": "CA", "display_address": ["2420 Industry St", "Oceanside, CA 92054"]}, "phone": "+17602013393", "display_phone": "(760) 201-3393", "distance": 17295.954200705084}, {"id": "QE4usCtkfNLOUpeALZm6Aw", "alias": "french-corner-encinitas", "name": "French Corner", "image_url": "https://s3-media3.fl.yelpcdn.com/bphoto/0Jm_y9HEbWlCofJ5wx_cjQ/o.jpg", "is_closed": false, "url": "https://www.yelp.com/biz/french-corner-encinitas?adjust_creative=oncXGL2aPIKrtJdnWeFSnA&utm_campaign=yelp_api_v3&utm_medium=api_v3_business_search&utm_source=oncXGL2aPIKrtJdnWeFSnA", "review_count": 223, "categories": [{"alias": "bakeries", "title": "Bakeries"}, {"alias": "sandwiches", "title": "Sandwiches"}, {"alias": "cafes", "title": "Cafes"}], "rating": 4.0, "coordinates": {"latitude": 33.0694548802243, "longitude": -117.304170951247}, "transactions": [], "price": "$$", "location": {"address1": "1200 N Coast Hwy 101", "address2": "", "address3": "", "city": "Encinitas", "zip_code": "92024", "country": "US", "state": "CA", "display_address": ["1200 N Coast Hwy 101", "Encinitas, CA 92024"]}, "phone": "+17602302221", "display_phone": "(760) 230-2221", "distance": 14587.941563447659}, {"id": "t2SxdyEdoLE800wJY7zLIA", "alias": "isabelle-briens-french-pastry-cafe-encinitas", "name": "Isabelle Briens French Pastry Cafe", "image_url": "https://s3-media1.fl.yelpcdn.com/bphoto/Vz14TCk-kdaq_aFZZVxpZQ/o.jpg", "is_closed": false, "url": "https://www.yelp.com/biz/isabelle-briens-french-pastry-cafe-encinitas?adjust_creative=oncXGL2aPIKrtJdnWeFSnA&utm_campaign=yelp_api_v3&utm_medium=api_v3_business_search&utm_source=oncXGL2aPIKrtJdnWeFSnA", "review_count": 157, "categories": [{"alias": "breakfast_brunch", "title": "Breakfast & Brunch"}, {"alias": "cafes", "title": "Cafes"}, {"alias": "bakeries", "title": "Bakeries"}], "rating": 4.0, "coordinates": {"latitude": 33.0480539936261, "longitude": -117.258074439339}, "transactions": [], "price": "$", "location": {"address1": "127 N El Camino Real", "address2": "", "address3": "", "city": "Encinitas", "zip_code": "92024", "country": "US", "state": "CA", "display_address": ["127 N El Camino Real", "Encinitas, CA 92024"]}, "phone": "+17609427891", "display_phone": "(760) 942-7891", "distance": 13053.596704825812}, {"id": "DxNhIGu1WuzX9RT4487bsg", "alias": "the-broken-yolk-cafe-carlsbad-2", "name": "The Broken Yolk Cafe", "image_url": "https://s3-media2.fl.yelpcdn.com/bphoto/vsH4Qd66kYAaQrqeDhwRRA/o.jpg", "is_closed": false, "url": "https://www.yelp.com/biz/the-broken-yolk-cafe-carlsbad-2?adjust_creative=oncXGL2aPIKrtJdnWeFSnA&utm_campaign=yelp_api_v3&utm_medium=api_v3_business_search&utm_source=oncXGL2aPIKrtJdnWeFSnA", "review_count": 525, "categories": [{"alias": "breakfast_brunch", "title": "Breakfast & Brunch"}, {"alias": "cafes", "title": "Cafes"}, {"alias": "tradamerican", "title": "American (Traditional)"}], "rating": 3.5, "coordinates": {"latitude": 33.0866318, "longitude": -117.2686025}, "transactions": [], "price": "$$", "location": {"address1": "7670 El Camino Real", "address2": "", "address3": "", "city": "Carlsbad", "zip_code": "92009", "country": "US", "state": "CA", "display_address": ["7670 El Camino Real", "Carlsbad, CA 92009"]}, "phone": "+17609438182", "display_phone": "(760) 943-8182", "distance": 10778.397896417022}, {"id": "-Q_wX-Y0GzmCn3YqkguHEw", "alias": "the-broken-yolk-cafe-oceanside", "name": "The Broken Yolk Cafe", "image_url": "https://s3-media4.fl.yelpcdn.com/bphoto/keSW9lICi5HV3cND9AB2Lg/o.jpg", "is_closed": false, "url": "https://www.yelp.com/biz/the-broken-yolk-cafe-oceanside?adjust_creative=oncXGL2aPIKrtJdnWeFSnA&utm_campaign=yelp_api_v3&utm_medium=api_v3_business_search&utm_source=oncXGL2aPIKrtJdnWeFSnA", "review_count": 856, "categories": [{"alias": "breakfast_brunch", "title": "Breakfast & Brunch"}, {"alias": "cafes", "title": "Cafes"}, {"alias": "tradamerican", "title": "American (Traditional)"}], "rating": 4.0, "coordinates": {"latitude": 33.183563, "longitude": -117.334792}, "transactions": ["delivery", "pickup"], "price": "$$", "location": {"address1": "2434 Vista Way", "address2": "", "address3": "", "city": "Oceanside", "zip_code": "92054", "country": "US", "state": "CA", "display_address": ["2434 Vista Way", "Oceanside, CA 92054"]}, "phone": "+17609679655", "display_phone": "(760) 967-9655", "distance": 15741.153648508185}, {"id": "XUHS784Hm0_o4EX4N73uKQ", "alias": "2good2b-encinitas-3", "name": "2Good2B", "image_url": "https://s3-media3.fl.yelpcdn.com/bphoto/ro8KsMPIHi-0BlBqOxXQHQ/o.jpg", "is_closed": false, "url": "https://www.yelp.com/biz/2good2b-encinitas-3?adjust_creative=oncXGL2aPIKrtJdnWeFSnA&utm_campaign=yelp_api_v3&utm_medium=api_v3_business_search&utm_source=oncXGL2aPIKrtJdnWeFSnA", "review_count": 473, "categories": [{"alias": "gluten_free", "title": "Gluten-Free"}, {"alias": "cafes", "title": "Cafes"}, {"alias": "bakeries", "title": "Bakeries"}], "rating": 4.0, "coordinates": {"latitude": 33.0491470553889, "longitude": -117.260507209262}, "transactions": ["pickup"], "price": "$$", "location": {"address1": "204 N El Camino Real", "address2": "Ste H", "address3": "", "city": "Encinitas", "zip_code": "92024", "country": "US", "state": "CA", "display_address": ["204 N El Camino Real", "Ste H", "Encinitas, CA 92024"]}, "phone": "+17609424663", "display_phone": "(760) 942-4663", "distance": 13096.334867181868}, {"id": "OVAnbzo3PgfvMSVvdwMokw", "alias": "champagne-french-bakery-cafe-encinitas", "name": "Champagne French Bakery Cafe", "image_url": "https://s3-media4.fl.yelpcdn.com/bphoto/xDllK06EyFXHGzqUGPltiA/o.jpg", "is_closed": false, "url": "https://www.yelp.com/biz/champagne-french-bakery-cafe-encinitas?adjust_creative=oncXGL2aPIKrtJdnWeFSnA&utm_campaign=yelp_api_v3&utm_medium=api_v3_business_search&utm_source=oncXGL2aPIKrtJdnWeFSnA", "review_count": 102, "categories": [{"alias": "bakeries", "title": "Bakeries"}, {"alias": "french", "title": "French"}, {"alias": "cafes", "title": "Cafes"}], "rating": 4.0, "coordinates": {"latitude": 33.03605, "longitude": -117.23843}, "transactions": ["delivery", "pickup"], "price": "$$", "location": {"address1": "162 S Rancho Santa Fe Rd", "address2": "", "address3": "", "city": "Encinitas", "zip_code": "92024", "country": "US", "state": "CA", "display_address": ["162 S Rancho Santa Fe Rd", "Encinitas, CA 92024"]}, "phone": "+17609449446", "display_phone": "(760) 944-9446", "distance": 13256.694808069224}, {"id": "OHSQwsNx1MQXZib8tF138w", "alias": "california-bistro-at-park-hyatt-aviara-carlsbad", "name": "California Bistro At Park Hyatt Aviara", "image_url": "https://s3-media3.fl.yelpcdn.com/bphoto/A_RxdNWzYMzjFmloiFKV6A/o.jpg", "is_closed": false, "url": "https://www.yelp.com/biz/california-bistro-at-park-hyatt-aviara-carlsbad?adjust_creative=oncXGL2aPIKrtJdnWeFSnA&utm_campaign=yelp_api_v3&utm_medium=api_v3_business_search&utm_source=oncXGL2aPIKrtJdnWeFSnA", "review_count": 70, "categories": [{"alias": "cafes", "title": "Cafes"}], "rating": 3.5, "coordinates": {"latitude": 33.0991573708083, "longitude": -117.285778130688}, "transactions": [], "price": "$$$", "location": {"address1": "7100 Aviara Resort Dr", "address2": "", "address3": "", "city": "Carlsbad", "zip_code": "92011", "country": "US", "state": "CA", "display_address": ["7100 Aviara Resort Dr", "Carlsbad, CA 92011"]}, "phone": "+17606036868", "display_phone": "(760) 603-6868", "distance": 11485.142259513063}, {"id": "OFYilFo53EWCHGSda5TYWA", "alias": "buccaneer-cafe-oceanside", "name": "Buccaneer Cafe", "image_url": "https://s3-media1.fl.yelpcdn.com/bphoto/FkJp9J3HX_CbBaZ5Sm9cgg/o.jpg", "is_closed": false, "url": "https://www.yelp.com/biz/buccaneer-cafe-oceanside?adjust_creative=oncXGL2aPIKrtJdnWeFSnA&utm_campaign=yelp_api_v3&utm_medium=api_v3_business_search&utm_source=oncXGL2aPIKrtJdnWeFSnA", "review_count": 234, "categories": [{"alias": "breakfast_brunch", "title": "Breakfast & Brunch"}, {"alias": "cafes", "title": "Cafes"}], "rating": 4.5, "coordinates": {"latitude": 33.176919, "longitude": -117.368568}, "transactions": [], "price": "$", "location": {"address1": "1508 S Pacific St", "address2": "", "address3": "", "city": "Oceanside", "zip_code": "92054", "country": "US", "state": "CA", "display_address": ["1508 S Pacific St", "Oceanside, CA 92054"]}, "phone": "+17606963471", "display_phone": "(760) 696-3471", "distance": 18597.07617816982}, {"id": "SDI71wkj7TiDN1LicFLGEg", "alias": "swamis-caf\u00e9-101-encinitas-2", "name": "Swami's Caf\u00e9 101", "image_url": "https://s3-media2.fl.yelpcdn.com/bphoto/DGNaVKonKpEqcvUO11SxSw/o.jpg", "is_closed": false, "url": "https://www.yelp.com/biz/swamis-caf%C3%A9-101-encinitas-2?adjust_creative=oncXGL2aPIKrtJdnWeFSnA&utm_campaign=yelp_api_v3&utm_medium=api_v3_business_search&utm_source=oncXGL2aPIKrtJdnWeFSnA", "review_count": 666, "categories": [{"alias": "breakfast_brunch", "title": "Breakfast & Brunch"}, {"alias": "cafes", "title": "Cafes"}], "rating": 3.5, "coordinates": {"latitude": 33.037, "longitude": -117.29219}, "transactions": [], "price": "$", "location": {"address1": "1163 S Coast Hwy 101", "address2": "", "address3": "", "city": "Encinitas", "zip_code": "92024", "country": "US", "state": "CA", "display_address": ["1163 S Coast Hwy 101", "Encinitas, CA 92024"]}, "phone": "+17609440612", "display_phone": "(760) 944-0612", "distance": 16048.939447593899}, {"id": "d32Unfq10BZx_OVk-a4A3w", "alias": "angelika-film-center-and-cafe-carmel-mountain-san-diego-2", "name": "Angelika Film Center & Cafe - Carmel Mountain", "image_url": "https://s3-media2.fl.yelpcdn.com/bphoto/i9hapCe2btBImQbyAXu0fg/o.jpg", "is_closed": false, "url": "https://www.yelp.com/biz/angelika-film-center-and-cafe-carmel-mountain-san-diego-2?adjust_creative=oncXGL2aPIKrtJdnWeFSnA&utm_campaign=yelp_api_v3&utm_medium=api_v3_business_search&utm_source=oncXGL2aPIKrtJdnWeFSnA", "review_count": 498, "categories": [{"alias": "movietheaters", "title": "Cinema"}, {"alias": "cafes", "title": "Cafes"}, {"alias": "bars", "title": "Bars"}], "rating": 4.0, "coordinates": {"latitude": 32.9812943640823, "longitude": -117.081950940192}, "transactions": [], "price": "$$", "location": {"address1": "11620 Carmel Mountain Rd", "address2": "", "address3": "", "city": "San Diego", "zip_code": "92128", "country": "US", "state": "CA", "display_address": ["11620 Carmel Mountain Rd", "San Diego, CA 92128"]}, "phone": "+18582072606", "display_phone": "(858) 207-2606", "distance": 19747.320505642816}, {"id": "hA90TbCg0EsG4EJGL_4kjw", "alias": "pipes-cafe-cardiff", "name": "Pipes Cafe", "image_url": "https://s3-media2.fl.yelpcdn.com/bphoto/bf9WhVbFUNjMZrljYPCz0Q/o.jpg", "is_closed": false, "url": "https://www.yelp.com/biz/pipes-cafe-cardiff?adjust_creative=oncXGL2aPIKrtJdnWeFSnA&utm_campaign=yelp_api_v3&utm_medium=api_v3_business_search&utm_source=oncXGL2aPIKrtJdnWeFSnA", "review_count": 444, "categories": [{"alias": "tradamerican", "title": "American (Traditional)"}, {"alias": "cafes", "title": "Cafes"}, {"alias": "breakfast_brunch", "title": "Breakfast & Brunch"}], "rating": 4.5, "coordinates": {"latitude": 33.0212014, "longitude": -117.2818451}, "transactions": [], "price": "$", "location": {"address1": "121 Liverpool Dr", "address2": "", "address3": "", "city": "Cardiff", "zip_code": "92007", "country": "US", "state": "CA", "display_address": ["121 Liverpool Dr", "Cardiff, CA 92007"]}, "phone": "+17606320056", "display_phone": "(760) 632-0056", "distance": 16771.702660922212}, {"id": "uzxb98jsclI4wtJfrHqnRA", "alias": "101-cafe-oceanside", "name": "101 Cafe", "image_url": "https://s3-media3.fl.yelpcdn.com/bphoto/A2cRjX43nEejkYnMgsEang/o.jpg", "is_closed": false, "url": "https://www.yelp.com/biz/101-cafe-oceanside?adjust_creative=oncXGL2aPIKrtJdnWeFSnA&utm_campaign=yelp_api_v3&utm_medium=api_v3_business_search&utm_source=oncXGL2aPIKrtJdnWeFSnA", "review_count": 261, "categories": [{"alias": "tradamerican", "title": "American (Traditional)"}, {"alias": "cafes", "title": "Cafes"}, {"alias": "breakfast_brunch", "title": "Breakfast & Brunch"}], "rating": 3.5, "coordinates": {"latitude": 33.1885658, "longitude": -117.3735669}, "transactions": ["pickup"], "price": "$", "location": {"address1": "631 S Coast Hwy", "address2": "", "address3": "", "city": "Oceanside", "zip_code": "92054", "country": "US", "state": "CA", "display_address": ["631 S Coast Hwy", "Oceanside, CA 92054"]}, "phone": "+17607225220", "display_phone": "(760) 722-5220", "distance": 19366.05682231465}, {"id": "UebHvy-F5vQTD7WHnaKdDg", "alias": "darshan-bakery-and-cafe-encinitas", "name": "Darshan Bakery & Cafe", "image_url": "https://s3-media4.fl.yelpcdn.com/bphoto/zc2yFbfR2H43069KkKu2KQ/o.jpg", "is_closed": false, "url": "https://www.yelp.com/biz/darshan-bakery-and-cafe-encinitas?adjust_creative=oncXGL2aPIKrtJdnWeFSnA&utm_campaign=yelp_api_v3&utm_medium=api_v3_business_search&utm_source=oncXGL2aPIKrtJdnWeFSnA", "review_count": 163, "categories": [{"alias": "bakeries", "title": "Bakeries"}, {"alias": "cafes", "title": "Cafes"}], "rating": 4.5, "coordinates": {"latitude": 33.0399768, "longitude": -117.2938212}, "transactions": [], "price": "$$", "location": {"address1": "949 2nd St", "address2": "", "address3": "", "city": "Encinitas", "zip_code": "92024", "country": "US", "state": "CA", "display_address": ["949 2nd St", "Encinitas, CA 92024"]}, "phone": "+17604361337", "display_phone": "(760) 436-1337", "distance": 15946.935633392264}, {"id": "-ZJVaXutyni9O9dou0sJTA", "alias": "campus-cafe-carlsbad", "name": "Campus Cafe", "image_url": "https://s3-media1.fl.yelpcdn.com/bphoto/cyjsjGYNkARnS83MdlvveA/o.jpg", "is_closed": false, "url": "https://www.yelp.com/biz/campus-cafe-carlsbad?adjust_creative=oncXGL2aPIKrtJdnWeFSnA&utm_campaign=yelp_api_v3&utm_medium=api_v3_business_search&utm_source=oncXGL2aPIKrtJdnWeFSnA", "review_count": 121, "categories": [{"alias": "delis", "title": "Delis"}, {"alias": "cafes", "title": "Cafes"}, {"alias": "sandwiches", "title": "Sandwiches"}], "rating": 4.5, "coordinates": {"latitude": 33.131802, "longitude": -117.270076}, "transactions": [], "price": "$", "location": {"address1": "5966 La Place Ct", "address2": "Ste 150", "address3": "", "city": "Carlsbad", "zip_code": "92008", "country": "US", "state": "CA", "display_address": ["5966 La Place Ct", "Ste 150", "Carlsbad, CA 92008"]}, "phone": "+17604319210", "display_phone": "(760) 431-9210", "distance": 9074.796138870406}, {"id": "n72--MemyttqRxtG599A9A", "alias": "honeys-bistro-encinitas", "name": "Honey's Bistro", "image_url": "https://s3-media3.fl.yelpcdn.com/bphoto/d9QMg9_8NGwhTUkfBHHTuw/o.jpg", "is_closed": false, "url": "https://www.yelp.com/biz/honeys-bistro-encinitas?adjust_creative=oncXGL2aPIKrtJdnWeFSnA&utm_campaign=yelp_api_v3&utm_medium=api_v3_business_search&utm_source=oncXGL2aPIKrtJdnWeFSnA", "review_count": 499, "categories": [{"alias": "breakfast_brunch", "title": "Breakfast & Brunch"}, {"alias": "cafes", "title": "Cafes"}, {"alias": "newamerican", "title": "American (New)"}], "rating": 4.0, "coordinates": {"latitude": 33.04415, "longitude": -117.29386}, "transactions": [], "price": "$$", "location": {"address1": "632 South Coast Hwy 101", "address2": "", "address3": "", "city": "Encinitas", "zip_code": "92024", "country": "US", "state": "CA", "display_address": ["632 South Coast Hwy 101", "Encinitas, CA 92024"]}, "phone": "+17609425433", "display_phone": "(760) 942-5433", "distance": 15597.75472158957}, {"id": "SqtnbJ2awhAYYZP0a2gYIw", "alias": "the-sandwich-spot-encinitas-2", "name": "The Sandwich Spot", "image_url": "https://s3-media3.fl.yelpcdn.com/bphoto/PpW-N3v4h3jqzMZ-SHh0Ag/o.jpg", "is_closed": false, "url": "https://www.yelp.com/biz/the-sandwich-spot-encinitas-2?adjust_creative=oncXGL2aPIKrtJdnWeFSnA&utm_campaign=yelp_api_v3&utm_medium=api_v3_business_search&utm_source=oncXGL2aPIKrtJdnWeFSnA", "review_count": 290, "categories": [{"alias": "sandwiches", "title": "Sandwiches"}, {"alias": "delis", "title": "Delis"}, {"alias": "cafes", "title": "Cafes"}], "rating": 4.0, "coordinates": {"latitude": 33.0490435418675, "longitude": -117.29460910975}, "transactions": ["pickup"], "price": "$$", "location": {"address1": "90 N Coast Hwy", "address2": "Ste 103", "address3": "", "city": "Encinitas", "zip_code": "92024", "country": "US", "state": "CA", "display_address": ["90 N Coast Hwy", "Ste 103", "Encinitas, CA 92024"]}, "phone": "+17602302147", "display_phone": "(760) 230-2147", "distance": 15279.122305535235}, {"id": "Fdu-9EWeCadd9BgdFEko2A", "alias": "pinpoint-cafe-del-mar", "name": "Pinpoint Cafe", "image_url": "https://s3-media2.fl.yelpcdn.com/bphoto/8YGAOxnz1g9CMQNAxjgmhA/o.jpg", "is_closed": false, "url": "https://www.yelp.com/biz/pinpoint-cafe-del-mar?adjust_creative=oncXGL2aPIKrtJdnWeFSnA&utm_campaign=yelp_api_v3&utm_medium=api_v3_business_search&utm_source=oncXGL2aPIKrtJdnWeFSnA", "review_count": 30, "categories": [{"alias": "juicebars", "title": "Juice Bars & Smoothies"}, {"alias": "cafes", "title": "Cafes"}, {"alias": "acaibowls", "title": "Acai Bowls"}], "rating": 5.0, "coordinates": {"latitude": 32.9687062595724, "longitude": -117.265311965659}, "transactions": ["pickup"], "price": "$", "location": {"address1": "2002 Jimmy Durante Blvd", "address2": null, "address3": "", "city": "Del Mar", "zip_code": "92014", "country": "US", "state": "CA", "display_address": ["2002 Jimmy Durante Blvd", "Del Mar, CA 92014"]}, "phone": "+16195193863", "display_phone": "(619) 519-3863", "distance": 21043.585568928112}, {"id": "mgcYQGQlUg8vpKt920RB8w", "alias": "board-and-brew-del-sur-del-sur-2", "name": "Board & Brew - Del Sur", "image_url": "https://s3-media3.fl.yelpcdn.com/bphoto/-A9pv7pZxkjRkYJKUn1Xlg/o.jpg", "is_closed": false, "url": "https://www.yelp.com/biz/board-and-brew-del-sur-del-sur-2?adjust_creative=oncXGL2aPIKrtJdnWeFSnA&utm_campaign=yelp_api_v3&utm_medium=api_v3_business_search&utm_source=oncXGL2aPIKrtJdnWeFSnA", "review_count": 176, "categories": [{"alias": "sandwiches", "title": "Sandwiches"}, {"alias": "beerbar", "title": "Beer Bar"}, {"alias": "cafes", "title": "Cafes"}], "rating": 4.5, "coordinates": {"latitude": 33.020259, "longitude": -117.1240315}, "transactions": [], "price": "$", "location": {"address1": "16480 Paseo Del Sur", "address2": "Ste 135", "address3": "", "city": "Del Sur", "zip_code": "92127", "country": "US", "state": "CA", "display_address": ["16480 Paseo Del Sur", "Ste 135", "Del Sur, CA 92127"]}, "phone": "+17603086886", "display_phone": "(760) 308-6886", "distance": 14245.249398860667}, {"id": "W3l2osudva-oIOz0o3Ecbg", "alias": "2good2b-rancho-bernardo-san-diego", "name": "2GOOD2B Rancho Bernardo", "image_url": "https://s3-media1.fl.yelpcdn.com/bphoto/QPVz88VH_8qfO0eE2ZZH4g/o.jpg", "is_closed": false, "url": "https://www.yelp.com/biz/2good2b-rancho-bernardo-san-diego?adjust_creative=oncXGL2aPIKrtJdnWeFSnA&utm_campaign=yelp_api_v3&utm_medium=api_v3_business_search&utm_source=oncXGL2aPIKrtJdnWeFSnA", "review_count": 157, "categories": [{"alias": "cafes", "title": "Cafes"}, {"alias": "gluten_free", "title": "Gluten-Free"}, {"alias": "bakeries", "title": "Bakeries"}], "rating": 4.0, "coordinates": {"latitude": 33.020043, "longitude": -117.0743331}, "transactions": ["delivery", "pickup"], "price": "$$", "location": {"address1": "11975 Bernardo Plaza Dr", "address2": null, "address3": "", "city": "San Diego", "zip_code": "92128", "country": "US", "state": "CA", "display_address": ["11975 Bernardo Plaza Dr", "San Diego, CA 92128"]}, "phone": "+18584874663", "display_phone": "(858) 487-4663", "distance": 16472.283623561274}], "total": 78, "region": {"center": {"longitude": -117.17330932617188, "latitude": 33.141533511091374}}}