{"businesses": [{"id": "nRKvaT9vmo_XwTRw6QK16Q", "alias": "surf-brothers-teriyaki-carlsbad", "name": "Surf Brothers Teriyaki", "image_url": "https://s3-media4.fl.yelpcdn.com/bphoto/Qw6in2aB9moeBBHhMa4LYQ/o.jpg", "is_closed": false, "url": "https://www.yelp.com/biz/surf-brothers-teriyaki-carlsbad?adjust_creative=oncXGL2aPIKrtJdnWeFSnA&utm_campaign=yelp_api_v3&utm_medium=api_v3_business_search&utm_source=oncXGL2aPIKrtJdnWeFSnA", "review_count": 251, "categories": [{"alias": "hawaiian", "title": "Hawaiian"}, {"alias": "bbq", "title": "Barbeque"}, {"alias": "hotdogs", "title": "Fast Food"}], "rating": 4.0, "coordinates": {"latitude": 33.13106, "longitude": -117.260566}, "transactions": [], "price": "$", "location": {"address1": "2708 Loker Ave W", "address2": "Ste 103", "address3": "", "city": "Carlsbad", "zip_code": "92010", "country": "US", "state": "CA", "display_address": ["2708 Loker Ave W", "Ste 103", "Carlsbad, CA 92010"]}, "phone": "+17604597973", "display_phone": "(760) 459-7973", "distance": 2804.601645486323}], "total": 1, "region": {"center": {"longitude": -117.28866577148438, "latitude": 33.12198326621279}}}